{
 "albums": {},
 "discs": {
  "disc.0345": {
   "album_total_tracks": 8,
   "album_track_offset": 0,
   "album_uniq_id": "marshall_our_island_story",
   "artist": "",
   "cddb_id": "72122809",
   "cddb_string": "72122809 9 150 35463 87944 116789 150487 205233 233957 278285 314010 4650",
   "disc_of_set": 2,
   "downloaded_artists": "",
   "downloaded_titles": "",
   "genre": "audiobook",
   "json_path": "source/naxos_our_island_story_disc_2/disc.json",
   "musicbrainz_id": "jyAT12BUgWMJ8SuCIaWoaA0Tiik-",
   "musicbrainz_release_id": "",
   "musicbrainz_string": "9 150 35463 87944 116789 150487 205233 233957 278285 314010 348750",
   "num_tracks": 9,
   "rip_data": "",
   "rip_date": "",
   "rip_time": "",
   "src_directory": "naxos_our_island_story_disc_2",
   "title": "",
   "total_length": 0,
   "tracks": [
    {
     "artist": "",
     "downloaded_artists": "",
     "downloaded_titles": "",
     "length_seconds": 0,
     "number": 1,
     "offset": 150,
     "output_artist": "H.E.Marshall",
     "output_title": "Track 1 of 9 of disc 1 of 13",
     "sectors": 0,
     "title": ""
    },
    {
     "artist": "",
     "downloaded_artists": "",
     "downloaded_titles": "",
     "length_seconds": 0,
     "number": 2,
     "offset": 35463,
     "output_artist": "H.E.Marshall",
     "output_title": "Track 2 of 9 of disc 1 of 13",
     "sectors": 0,
     "title": ""
    },
    {
     "artist": "",
     "downloaded_artists": "",
     "downloaded_titles": "",
     "length_seconds": 0,
     "number": 3,
     "offset": 87944,
     "output_artist": "H.E.Marshall",
     "output_title": "Track 3 of 9 of disc 1 of 13",
     "sectors": 0,
     "title": ""
    },
    {
     "artist": "",
     "downloaded_artists": "",
     "downloaded_titles": "",
     "length_seconds": 0,
     "number": 4,
     "offset": 116789,
     "output_artist": "H.E.Marshall",
     "output_title": "Track 4 of 9 of disc 1 of 13",
     "sectors": 0,
     "title": ""
    },
    {
     "artist": "",
     "downloaded_artists": "",
     "downloaded_titles": "",
     "length_seconds": 0,
     "number": 5,
     "offset": 150487,
     "output_artist": "H.E.Marshall",
     "output_title": "Track 5 of 9 of disc 1 of 13",
     "sectors": 0,
     "title": ""
    },
    {
     "artist": "",
     "downloaded_artists": "",
     "downloaded_titles": "",
     "length_seconds": 0,
     "number": 6,
     "offset": 205233,
     "output_artist": "H.E.Marshall",
     "output_title": "Track 6 of 9 of disc 1 of 13",
     "sectors": 0,
     "title": ""
    },
    {
     "artist": "",
     "downloaded_artists": "",
     "downloaded_titles": "",
     "length_seconds": 0,
     "number": 7,
     "offset": 233957,
     "output_artist": "H.E.Marshall",
     "output_title": "Track 7 of 9 of disc 1 of 13",
     "sectors": 0,
     "title": ""
    },
    {
     "artist": "",
     "downloaded_artists": "",
     "downloaded_titles": "",
     "length_seconds": 0,
     "number": 8,
     "offset": 278285,
     "output_artist": "H.E.Marshall",
     "output_title": "Track 8 of 9 of disc 1 of 13",
     "sectors": 0,
     "title": ""
    },
    {
     "artist": "",
     "downloaded_artists": "",
     "downloaded_titles": "",
     "length_seconds": 0,
     "number": 9,
     "offset": 314010,
     "output_artist": "H.E.Marshall",
     "output_title": "Track 9 of 9 of disc 1 of 13",
     "sectors": 0,
     "title": ""
    }
   ]
  }
 }
}