{
 "albums": {},
 "discs": {
  "disc.0398": {
   "album_total_tracks": 35,
   "album_track_offset": 0,
   "album_uniq_id": "alb.0172",
   "artist": "",
   "cddb_id": "0a121423",
   "cddb_string": "0a121423 35 182 31607 34295 37172 50037 53972 72992 75625 96842 105427 108615 120147 125972 139190 143165 146957 150842 154715 161302 170117 192367 195180 199202 217335 222385 226680 237607 262170 270295 297897 313668 317608 320530 325180 330868 4630",
   "disc_of_set": 1,
   "downloaded_artists": "Johann Sebastian Bach; John Eliot Gardiner, The Monteverdi Choir, The London Oratory Junior Choir, The English Baroque Soloists",
   "downloaded_titles": "St. Matthew Passion",
   "genre": "choral",
   "json_path": "source/john_eliot_gardiner_bach_matthew_passion_disc_1/disc.json",
   "musicbrainz_id": "MOQ57K5urPz9_JNpWjvrhNnBH.M-",
   "musicbrainz_release_id": "51d08afb-0d81-4617-8c33-979806910ddf",
   "musicbrainz_string": "35 182 31607 34295 37172 50037 53972 72992 75625 96842 105427 108615 120147 125972 139190 143165 146957 150842 154715 161302 170117 192367 195180 199202 217335 222385 226680 237607 262170 270295 297897 313668 317608 320530 325180 330868 347250",
   "num_tracks": 35,
   "rip_data": "",
   "rip_date": "",
   "rip_time": "",
   "src_directory": "john_eliot_gardiner_bach_matthew_passion_disc_1",
   "title": "",
   "total_length": 0,
   "tracks": [
    {
     "artist": "",
     "downloaded_artists": "",
     "downloaded_titles": "St. Matthew Passion, BWV 244: Teil I. Chorus \"Kommt, ihr T\u00f6chter, helft mir klagen\" - Choral \"O Lamm Gottes, unschuldig\"",
     "length_seconds": 419000,
     "number": 1,
     "offset": 183,
     "output_artist": "Johann Sebastian Bach; John Eliot Gardiner, The Monteverdi Choir, The London Oratory Junior Choir, The English Baroque Soloists",
     "output_title": "St. Matthew Passion, BWV 244: Teil I. Chorus \"Kommt, ihr T\u00f6chter, helft mir klagen\" - Choral \"O Lamm Gottes, unschuldig\"",
     "sectors": 31425,
     "title": "Teil I. 1 Chorus \"Kommt, ihr T\u00f6chter, helft mir klagen\" - Choral \"O Lamm Gottes, unschuldig\""
    },
    {
     "artist": "",
     "downloaded_artists": "",
     "downloaded_titles": "St. Matthew Passion, BWV 244: Teil I. \"Da Jesus diese Rede vollendet hatte\" (Evangelista, Jesus)",
     "length_seconds": 35826,
     "number": 2,
     "offset": 31608,
     "output_artist": "Johann Sebastian Bach; John Eliot Gardiner, The Monteverdi Choir, The London Oratory Junior Choir, The English Baroque Soloists",
     "output_title": "St. Matthew Passion, BWV 244: Teil I. \"Da Jesus diese Rede vollendet hatte\" (Evangelista, Jesus)",
     "sectors": 2687,
     "title": "Teil I. 2 \"Da Jesus diese Rede vollendet hatte\" (Evangelista, Jesus)"
    },
    {
     "artist": "",
     "downloaded_artists": "",
     "downloaded_titles": "St. Matthew Passion, BWV 244: Teil I. Choral \"Herzliebster Jesu, was hast du verbrochen\"",
     "length_seconds": 38773,
     "number": 3,
     "offset": 34295,
     "output_artist": "Johann Sebastian Bach; John Eliot Gardiner, The Monteverdi Choir, The London Oratory Junior Choir, The English Baroque Soloists",
     "output_title": "St. Matthew Passion, BWV 244: Teil I. Choral \"Herzliebster Jesu, was hast du verbrochen\"",
     "sectors": 2878,
     "title": "Teil I. 3 Choral \"Herzliebster Jesu, was hast du verbrochen\""
    },
    {
     "artist": "",
     "downloaded_artists": "",
     "downloaded_titles": "St. Matthew Passion, BWV 244: Teil I. \"Da versammelten sich die Hohenpriester\" (Evangelista) - Chori \"Ja nicht auf das Fest\" - \"Da nun Jesus war zu Bethanien\" (Evangelista) - Chorus \"Wozu dienet dieser Unrat\" - \"Da das Jesus merkete\" (Evangelista, Jesus)",
     "length_seconds": 171533,
     "number": 4,
     "offset": 37173,
     "output_artist": "Johann Sebastian Bach; John Eliot Gardiner, The Monteverdi Choir, The London Oratory Junior Choir, The English Baroque Soloists",
     "output_title": "St. Matthew Passion, BWV 244: Teil I. \"Da versammelten sich die Hohenpriester\" (Evangelista) - Chori \"Ja nicht auf das Fest\" - \"Da nun Jesus war zu Bethanien\" (Evangelista) - Chorus \"Wozu dienet dieser Unrat\" - \"Da das Jesus merkete\" (Evangelista, Jesus)",
     "sectors": 12865,
     "title": "Teil I. 4 \"Da versammelten sich die Hohenpriester\" (Evangelista) - Chori \"Ja nicht auf das Fest\" - \"Da nun Jesus war zu Bethanien\" (Evangelista) - Chorus \"Wozu dienet dieser Unrat\" - \"Da das Jesus merkete\" (Evangelista, Jesus)"
    },
    {
     "artist": "",
     "downloaded_artists": "",
     "downloaded_titles": "St. Matthew Passion, BWV 244: Teil I. Recitativo (Alt) \"Du lieber Heiland du\"",
     "length_seconds": 52533,
     "number": 5,
     "offset": 50038,
     "output_artist": "Johann Sebastian Bach; John Eliot Gardiner, The Monteverdi Choir, The London Oratory Junior Choir, The English Baroque Soloists",
     "output_title": "St. Matthew Passion, BWV 244: Teil I. Recitativo (Alt) \"Du lieber Heiland du\"",
     "sectors": 3935,
     "title": "Teil I. 5 Recitativo (Alt) \"Du lieber Heiland du\""
    },
    {
     "artist": "",
     "downloaded_artists": "",
     "downloaded_titles": "St. Matthew Passion, BWV 244: Teil I. Aria (Alt) \"Buss und Reu\"",
     "length_seconds": 253600,
     "number": 6,
     "offset": 53973,
     "output_artist": "Johann Sebastian Bach; John Eliot Gardiner, The Monteverdi Choir, The London Oratory Junior Choir, The English Baroque Soloists",
     "output_title": "St. Matthew Passion, BWV 244: Teil I. Aria (Alt) \"Buss und Reu\"",
     "sectors": 19020,
     "title": "Teil I. 6 Aria (Alt) \"Buss und Reu\""
    },
    {
     "artist": "",
     "downloaded_artists": "",
     "downloaded_titles": "St. Matthew Passion, BWV 244: Teil I. \"Da ging hin der Zw\u00f6lfen einer\" (Evangelista, Judas)",
     "length_seconds": 35093,
     "number": 7,
     "offset": 72993,
     "output_artist": "Johann Sebastian Bach; John Eliot Gardiner, The Monteverdi Choir, The London Oratory Junior Choir, The English Baroque Soloists",
     "output_title": "St. Matthew Passion, BWV 244: Teil I. \"Da ging hin der Zw\u00f6lfen einer\" (Evangelista, Judas)",
     "sectors": 2632,
     "title": "Teil I. 7 \"Da ging hin der Zw\u00f6lfen einer\" (Evangelista, Judas)"
    },
    {
     "artist": "",
     "downloaded_artists": "",
     "downloaded_titles": "St. Matthew Passion, BWV 244: Teil I. Aria (Sopran) \"Blute nur, du liebes Herz\"",
     "length_seconds": 282906,
     "number": 8,
     "offset": 75625,
     "output_artist": "Johann Sebastian Bach; John Eliot Gardiner, The Monteverdi Choir, The London Oratory Junior Choir, The English Baroque Soloists",
     "output_title": "St. Matthew Passion, BWV 244: Teil I. Aria (Sopran) \"Blute nur, du liebes Herz\"",
     "sectors": 21218,
     "title": "Teil I. 8 Aria (Sopran) \"Blute nur, du liebes Herz\""
    },
    {
     "artist": "",
     "downloaded_artists": "",
     "downloaded_titles": "St. Matthew Passion, BWV 244: Teil I. \"Aber am ersten Tage der s\u00fcssen Brot\" (Evangelista) - Chorus \"Wo willst du, dass wir dir bereiten\" - \"Er sprach: Gehet hin in die Stadt\" (Evangelista, Jesus) - \"Und sie wurden sehr betr\u00fcbt\" (Evangelista) -",
     "length_seconds": 114466,
     "number": 9,
     "offset": 96843,
     "output_artist": "Johann Sebastian Bach; John Eliot Gardiner, The Monteverdi Choir, The London Oratory Junior Choir, The English Baroque Soloists",
     "output_title": "St. Matthew Passion, BWV 244: Teil I. \"Aber am ersten Tage der s\u00fcssen Brot\" (Evangelista) - Chorus \"Wo willst du, dass wir dir bereiten\" - \"Er sprach: Gehet hin in die Stadt\" (Evangelista, Jesus) - \"Und sie wurden sehr betr\u00fcbt\" (Evangelista) -",
     "sectors": 8585,
     "title": "Teil I. 9 \"Aber am ersten Tage der s\u00fcssen Brot\" (Evangelista) - Chorus \"Wo willst du, dass wir dir bereiten\" - \"Er sprach: Gehet hin in die Stadt\" (Evangelista, Jesus) - \"Und sie wurden sehr betr\u00fcbt\" (Evangelista) -"
    },
    {
     "artist": "",
     "downloaded_artists": "",
     "downloaded_titles": "St. Matthew Passion, BWV 244: Teil I. Choral \"Ich bin's, ich sollte b\u00fcssen\"",
     "length_seconds": 42493,
     "number": 10,
     "offset": 105428,
     "output_artist": "Johann Sebastian Bach; John Eliot Gardiner, The Monteverdi Choir, The London Oratory Junior Choir, The English Baroque Soloists",
     "output_title": "St. Matthew Passion, BWV 244: Teil I. Choral \"Ich bin's, ich sollte b\u00fcssen\"",
     "sectors": 3187,
     "title": "Teil I. 10 Choral \"Ich bin's, ich sollte b\u00fcssen\""
    },
    {
     "artist": "",
     "downloaded_artists": "",
     "downloaded_titles": "St. Matthew Passion, BWV 244: Teil I. \"Er antwortete und sprach\" (Evangelista, Jesus, Judas)",
     "length_seconds": 153773,
     "number": 11,
     "offset": 108615,
     "output_artist": "Johann Sebastian Bach; John Eliot Gardiner, The Monteverdi Choir, The London Oratory Junior Choir, The English Baroque Soloists",
     "output_title": "St. Matthew Passion, BWV 244: Teil I. \"Er antwortete und sprach\" (Evangelista, Jesus, Judas)",
     "sectors": 11533,
     "title": "Teil I. 11 \"Er antwortete und sprach\" (Evangelista, Jesus, Judas)"
    },
    {
     "artist": "",
     "downloaded_artists": "",
     "downloaded_titles": "St. Matthew Passion, BWV 244: Teil I. Recitativo (Sopran) \"Wiewohl mein Herz in Tr\u00e4nen schwimmt\"",
     "length_seconds": 77666,
     "number": 12,
     "offset": 120148,
     "output_artist": "Johann Sebastian Bach; John Eliot Gardiner, The Monteverdi Choir, The London Oratory Junior Choir, The English Baroque Soloists",
     "output_title": "St. Matthew Passion, BWV 244: Teil I. Recitativo (Sopran) \"Wiewohl mein Herz in Tr\u00e4nen schwimmt\"",
     "sectors": 5825,
     "title": "Teil I. 12 Recitativo (Sopran) \"Wiewohl mein Herz in Tr\u00e4nen schwimmt\""
    },
    {
     "artist": "",
     "downloaded_artists": "",
     "downloaded_titles": "St. Matthew Passion, BWV 244: Teil I. Aria (Sopran) \"Ich will dir mein Herze schenken\"",
     "length_seconds": 176226,
     "number": 13,
     "offset": 125973,
     "output_artist": "Johann Sebastian Bach; John Eliot Gardiner, The Monteverdi Choir, The London Oratory Junior Choir, The English Baroque Soloists",
     "output_title": "St. Matthew Passion, BWV 244: Teil I. Aria (Sopran) \"Ich will dir mein Herze schenken\"",
     "sectors": 13217,
     "title": "Teil I. 13 Aria (Sopran) \"Ich will dir mein Herze schenken\""
    },
    {
     "artist": "",
     "downloaded_artists": "",
     "downloaded_titles": "St. Matthew Passion, BWV 244: Teil I. \"Und da sie den Lobgesang gesprochen hatten\" (Evangelista, Judas)",
     "length_seconds": 53000,
     "number": 14,
     "offset": 139190,
     "output_artist": "Johann Sebastian Bach; John Eliot Gardiner, The Monteverdi Choir, The London Oratory Junior Choir, The English Baroque Soloists",
     "output_title": "St. Matthew Passion, BWV 244: Teil I. \"Und da sie den Lobgesang gesprochen hatten\" (Evangelista, Judas)",
     "sectors": 3975,
     "title": "Teil I. 14 \"Und da sie den Lobgesang gesprochen hatten\" (Evangelista, Judas)"
    },
    {
     "artist": "",
     "downloaded_artists": "",
     "downloaded_titles": "St. Matthew Passion, BWV 244: Teil I. Choral \"Erkenne mich, mein H\u00fcter\"",
     "length_seconds": 50560,
     "number": 15,
     "offset": 143165,
     "output_artist": "Johann Sebastian Bach; John Eliot Gardiner, The Monteverdi Choir, The London Oratory Junior Choir, The English Baroque Soloists",
     "output_title": "St. Matthew Passion, BWV 244: Teil I. Choral \"Erkenne mich, mein H\u00fcter\"",
     "sectors": 3793,
     "title": "Teil I. 15 Choral \"Erkenne mich, mein H\u00fcter\""
    },
    {
     "artist": "",
     "downloaded_artists": "",
     "downloaded_titles": "St. Matthew Passion, BWV 244: Teil I. \"Petrus aber antwortete und sprach zu ihm\" (Evangelista, Petrus, Jesus)",
     "length_seconds": 51800,
     "number": 16,
     "offset": 146958,
     "output_artist": "Johann Sebastian Bach; John Eliot Gardiner, The Monteverdi Choir, The London Oratory Junior Choir, The English Baroque Soloists",
     "output_title": "St. Matthew Passion, BWV 244: Teil I. \"Petrus aber antwortete und sprach zu ihm\" (Evangelista, Petrus, Jesus)",
     "sectors": 3885,
     "title": "Teil I. 16 \"Petrus aber antwortete und sprach zu ihm\" (Evangelista, Petrus, Jesus)"
    },
    {
     "artist": "",
     "downloaded_artists": "",
     "downloaded_titles": "St. Matthew Passion, BWV 244: Teil I. Choral \"Ich will hier bei dir stehen\"",
     "length_seconds": 51853,
     "number": 17,
     "offset": 150843,
     "output_artist": "Johann Sebastian Bach; John Eliot Gardiner, The Monteverdi Choir, The London Oratory Junior Choir, The English Baroque Soloists",
     "output_title": "St. Matthew Passion, BWV 244: Teil I. Choral \"Ich will hier bei dir stehen\"",
     "sectors": 3872,
     "title": "Teil I. 17 Choral \"Ich will hier bei dir stehen\""
    },
    {
     "artist": "",
     "downloaded_artists": "",
     "downloaded_titles": "St. Matthew Passion, BWV 244: Teil I. \"Da kam Jesus mit ihnen zu einen Hofe\" (Evangelista, Jesus)",
     "length_seconds": 87826,
     "number": 18,
     "offset": 154715,
     "output_artist": "Johann Sebastian Bach; John Eliot Gardiner, The Monteverdi Choir, The London Oratory Junior Choir, The English Baroque Soloists",
     "output_title": "St. Matthew Passion, BWV 244: Teil I. \"Da kam Jesus mit ihnen zu einen Hofe\" (Evangelista, Jesus)",
     "sectors": 6588,
     "title": "Teil I. 18 \"Da kam Jesus mit ihnen zu einen Hofe\" (Evangelista, Jesus)"
    },
    {
     "artist": "",
     "downloaded_artists": "",
     "downloaded_titles": "St. Matthew Passion, BWV 244: Teil I. Recitativo (Tenor) \"O Schmerz! Hier zittert das gequ\u00e4lte Herz\" - Choral \"Was ist die Ursach' aller solcher Plagen\"",
     "length_seconds": 117533,
     "number": 19,
     "offset": 161303,
     "output_artist": "Johann Sebastian Bach; John Eliot Gardiner, The Monteverdi Choir, The London Oratory Junior Choir, The English Baroque Soloists",
     "output_title": "St. Matthew Passion, BWV 244: Teil I. Recitativo (Tenor) \"O Schmerz! Hier zittert das gequ\u00e4lte Herz\" - Choral \"Was ist die Ursach' aller solcher Plagen\"",
     "sectors": 8815,
     "title": "Teil I. 19 Recitativo (Tenor) \"O Schmerz! Hier zittert das gequ\u00e4lte Herz\" - Choral \"Was ist die Ursach' aller solcher Plagen\""
    },
    {
     "artist": "",
     "downloaded_artists": "",
     "downloaded_titles": "St. Matthew Passion, BWV 244: Teil I. Aria (Tenor) \"Ich will bei meinen Jesu wachen\" - Chorus \"So schlafen unsre S\u00fcnden ein\"",
     "length_seconds": 296720,
     "number": 20,
     "offset": 170118,
     "output_artist": "Johann Sebastian Bach; John Eliot Gardiner, The Monteverdi Choir, The London Oratory Junior Choir, The English Baroque Soloists",
     "output_title": "St. Matthew Passion, BWV 244: Teil I. Aria (Tenor) \"Ich will bei meinen Jesu wachen\" - Chorus \"So schlafen unsre S\u00fcnden ein\"",
     "sectors": 22250,
     "title": "Teil I. 20 Aria (Tenor) \"Ich will bei meinen Jesu wachen\" - Chorus \"So schlafen unsre S\u00fcnden ein\""
    },
    {
     "artist": "",
     "downloaded_artists": "",
     "downloaded_titles": "St. Matthew Passion, BWV 244: Teil I. \"Und ging hin ein wenig\" (Evangelista, Jesus)",
     "length_seconds": 37493,
     "number": 21,
     "offset": 192368,
     "output_artist": "Johann Sebastian Bach; John Eliot Gardiner, The Monteverdi Choir, The London Oratory Junior Choir, The English Baroque Soloists",
     "output_title": "St. Matthew Passion, BWV 244: Teil I. \"Und ging hin ein wenig\" (Evangelista, Jesus)",
     "sectors": 2812,
     "title": "Teil I. 21 \"Und ging hin ein wenig\" (Evangelista, Jesus)"
    },
    {
     "artist": "",
     "downloaded_artists": "",
     "downloaded_titles": "St. Matthew Passion, BWV 244: Teil I. Recitativo (Bass) \"Der Heiland f\u00e4llt vor seinem Vater nieder\"",
     "length_seconds": 53600,
     "number": 22,
     "offset": 195180,
     "output_artist": "Johann Sebastian Bach; John Eliot Gardiner, The Monteverdi Choir, The London Oratory Junior Choir, The English Baroque Soloists",
     "output_title": "St. Matthew Passion, BWV 244: Teil I. Recitativo (Bass) \"Der Heiland f\u00e4llt vor seinem Vater nieder\"",
     "sectors": 4023,
     "title": "Teil I. 22 Recitativo (Bass) \"Der Heiland f\u00e4llt vor seinem Vater nieder\""
    },
    {
     "artist": "",
     "downloaded_artists": "",
     "downloaded_titles": "St. Matthew Passion, BWV 244: Teil I. Aria (Bass) \"Gerne will ich mich bequemen\"",
     "length_seconds": 241866,
     "number": 23,
     "offset": 199203,
     "output_artist": "Johann Sebastian Bach; John Eliot Gardiner, The Monteverdi Choir, The London Oratory Junior Choir, The English Baroque Soloists",
     "output_title": "St. Matthew Passion, BWV 244: Teil I. Aria (Bass) \"Gerne will ich mich bequemen\"",
     "sectors": 18132,
     "title": "Teil I. 23 Aria (Bass) \"Gerne will ich mich bequemen\""
    },
    {
     "artist": "",
     "downloaded_artists": "",
     "downloaded_titles": "St. Matthew Passion, BWV 244: Teil I. \"Und er kam zu seinen J\u00fcngern\" (Evangelista, Jesus)",
     "length_seconds": 67333,
     "number": 24,
     "offset": 217335,
     "output_artist": "Johann Sebastian Bach; John Eliot Gardiner, The Monteverdi Choir, The London Oratory Junior Choir, The English Baroque Soloists",
     "output_title": "St. Matthew Passion, BWV 244: Teil I. \"Und er kam zu seinen J\u00fcngern\" (Evangelista, Jesus)",
     "sectors": 5050,
     "title": "Teil I. 24 \"Und er kam zu seinen J\u00fcngern\" (Evangelista, Jesus)"
    },
    {
     "artist": "",
     "downloaded_artists": "",
     "downloaded_titles": "St. Matthew Passion, BWV 244: Teil I. Choral \"Was mein Gott will, das g'scheh allzeit\"",
     "length_seconds": 57386,
     "number": 25,
     "offset": 222385,
     "output_artist": "Johann Sebastian Bach; John Eliot Gardiner, The Monteverdi Choir, The London Oratory Junior Choir, The English Baroque Soloists",
     "output_title": "St. Matthew Passion, BWV 244: Teil I. Choral \"Was mein Gott will, das g'scheh allzeit\"",
     "sectors": 4295,
     "title": "Teil I. 25 Choral \"Was mein Gott will, das g'scheh allzeit\""
    },
    {
     "artist": "",
     "downloaded_artists": "",
     "downloaded_titles": "St. Matthew Passion, BWV 244: Teil I. \"Und er kam und fand sie aber schlafend\" (Evangelista, Jesus, Judas)",
     "length_seconds": 145693,
     "number": 26,
     "offset": 226680,
     "output_artist": "Johann Sebastian Bach; John Eliot Gardiner, The Monteverdi Choir, The London Oratory Junior Choir, The English Baroque Soloists",
     "output_title": "St. Matthew Passion, BWV 244: Teil I. \"Und er kam und fand sie aber schlafend\" (Evangelista, Jesus, Judas)",
     "sectors": 10928,
     "title": "Teil I. 26 \"Und er kam und fand sie aber schlafend\" (Evangelista, Jesus, Judas)"
    },
    {
     "artist": "",
     "downloaded_artists": "",
     "downloaded_titles": "St. Matthew Passion, BWV 244: Teil I. Aria (Duett: Sopran, Alt) \"So ist mein Jesus nun gefangen\" - Chorus \"Lasst ihn, haltet, bindet nicht\" - Chori \"Sind Blitze, sind Donner in Wolken verschwunden?\"",
     "length_seconds": 327693,
     "number": 27,
     "offset": 237608,
     "output_artist": "Johann Sebastian Bach; John Eliot Gardiner, The Monteverdi Choir, The London Oratory Junior Choir, The English Baroque Soloists",
     "output_title": "St. Matthew Passion, BWV 244: Teil I. Aria (Duett: Sopran, Alt) \"So ist mein Jesus nun gefangen\" - Chorus \"Lasst ihn, haltet, bindet nicht\" - Chori \"Sind Blitze, sind Donner in Wolken verschwunden?\"",
     "sectors": 24562,
     "title": "Teil I. 27 Aria (Duett: Sopran, Alt) \"So ist mein Jesus nun gefangen\" - Chorus \"Lasst ihn, haltet, bindet nicht\" - Chori \"Sind Blitze, sind Donner in Wolken verschwunden?\""
    },
    {
     "artist": "",
     "downloaded_artists": "",
     "downloaded_titles": "St. Matthew Passion, BWV 244: Teil I. \"Und siehe, einer aus denen, die mit Jesu waren\" (Evangelista, Jesus)",
     "length_seconds": 108333,
     "number": 28,
     "offset": 262170,
     "output_artist": "Johann Sebastian Bach; John Eliot Gardiner, The Monteverdi Choir, The London Oratory Junior Choir, The English Baroque Soloists",
     "output_title": "St. Matthew Passion, BWV 244: Teil I. \"Und siehe, einer aus denen, die mit Jesu waren\" (Evangelista, Jesus)",
     "sectors": 8125,
     "title": "Teil I. 28 \"Und siehe, einer aus denen, die mit Jesu waren\" (Evangelista, Jesus)"
    },
    {
     "artist": "",
     "downloaded_artists": "",
     "downloaded_titles": "St. Matthew Passion, BWV 244: Teil I. Choral \"O Mensch, bewein dein S\u00fcnde gross\"",
     "length_seconds": 361506,
     "number": 29,
     "offset": 270295,
     "output_artist": "Johann Sebastian Bach; John Eliot Gardiner, The Monteverdi Choir, The London Oratory Junior Choir, The English Baroque Soloists",
     "output_title": "St. Matthew Passion, BWV 244: Teil I. Choral \"O Mensch, bewein dein S\u00fcnde gross\"",
     "sectors": 27113,
     "title": "Teil I. 29 Choral \"O Mensch, bewein dein S\u00fcnde gross\""
    },
    {
     "artist": "",
     "downloaded_artists": "",
     "downloaded_titles": "St. Matthew Passion, BWV 244: Teil II. \"Da nahmen die Kriegsknechte\" (Evangelista) - Chori \"Gegr\u00fcsset seist du, J\u00fcdenk\u00f6nig\" - \"Und speieten ihn an\" (Evangelista)###St. Matthew Passion, BWV 244: Teil II. Aria (Alt) \"Ach! nun ist mein Jesus hin\" - Chorus \"Wo ist denn dein Freund hingegangen\"",
     "length_seconds": 209813,
     "number": 30,
     "offset": 182,
     "output_artist": "Johann Sebastian Bach; John Eliot Gardiner, The Monteverdi Choir, The London Oratory Junior Choir, The English Baroque Soloists",
     "output_title": "St. Matthew Passion, BWV 244: Teil II. \"Da nahmen die Kriegsknechte\" (Evangelista) - Chori \"Gegr\u00fcsset seist du, J\u00fcdenk\u00f6nig\" - \"Und speieten ihn an\" (Evangelista)",
     "sectors": 15738,
     "title": "Teil II. 30 \"Da nahmen die Kriegsknechte\" (Evangelista) - Chori \"Gegr\u00fcsset seist du, J\u00fcdenk\u00f6nig\" - \"Und speieten ihn an\" (Evangelista)"
    },
    {
     "artist": "",
     "downloaded_artists": "",
     "downloaded_titles": "St. Matthew Passion, BWV 244: Teil II. Choral \"O Haupt voll Blut und Wunden\"###St. Matthew Passion, BWV 244: Teil II. \"Die aber Jesum gegriffen hatten\" (Evangelista)",
     "length_seconds": 52506,
     "number": 31,
     "offset": 15920,
     "output_artist": "Johann Sebastian Bach; John Eliot Gardiner, The Monteverdi Choir, The London Oratory Junior Choir, The English Baroque Soloists",
     "output_title": "St. Matthew Passion, BWV 244: Teil II. Choral \"O Haupt voll Blut und Wunden\"",
     "sectors": 3940,
     "title": "Teil II. 31 Choral \"O Haupt voll Blut und Wunden\""
    },
    {
     "artist": "",
     "downloaded_artists": "",
     "downloaded_titles": "St. Matthew Passion, BWV 244: Teil II. \"Und da sie ihn verspottet hatten\" (Evangelista)###St. Matthew Passion, BWV 244: Teil II. Choral \"Mir hat die Welt tr\u00fcglich gericht'\"",
     "length_seconds": 38973,
     "number": 32,
     "offset": 19860,
     "output_artist": "Johann Sebastian Bach; John Eliot Gardiner, The Monteverdi Choir, The London Oratory Junior Choir, The English Baroque Soloists",
     "output_title": "St. Matthew Passion, BWV 244: Teil II. \"Und da sie ihn verspottet hatten\" (Evangelista)",
     "sectors": 2922,
     "title": "Teil II. 32 \"Und da sie ihn verspottet hatten\" (Evangelista)"
    },
    {
     "artist": "",
     "downloaded_artists": "",
     "downloaded_titles": "St. Matthew Passion, BWV 244: Teil II. Recitativo (Bass) \"Ja freilich will in uns das Fleisch und Blut\"###St. Matthew Passion, BWV 244: Teil II. \"Und wiewohl viel falsche Zeugen herzutraten\" (Evangelista, Testis I/II, Pontifex)",
     "length_seconds": 62000,
     "number": 33,
     "offset": 22782,
     "output_artist": "Johann Sebastian Bach; John Eliot Gardiner, The Monteverdi Choir, The London Oratory Junior Choir, The English Baroque Soloists",
     "output_title": "St. Matthew Passion, BWV 244: Teil II. Recitativo (Bass) \"Ja freilich will in uns das Fleisch und Blut\"",
     "sectors": 4650,
     "title": "Teil II. 33 Recitativo (Bass) \"Ja freilich will in uns das Fleisch und Blut\""
    },
    {
     "artist": "",
     "downloaded_artists": "",
     "downloaded_titles": "St. Matthew Passion, BWV 244: Teil II. Aria (Bass) \"Komm, s\u00fcsses Kreuz, so will ich sagen\"###St. Matthew Passion, BWV 244: Teil II. Recitativo (Tenor) \"Mein Jesus schweigt zu falschen L\u00fcgen stille\"",
     "length_seconds": 75826,
     "number": 34,
     "offset": 27432,
     "output_artist": "Johann Sebastian Bach; John Eliot Gardiner, The Monteverdi Choir, The London Oratory Junior Choir, The English Baroque Soloists",
     "output_title": "St. Matthew Passion, BWV 244: Teil II. Aria (Bass) \"Komm, s\u00fcsses Kreuz, so will ich sagen\"",
     "sectors": 5688,
     "title": "Teil II. 34 Aria (Bass) \"Komm, s\u00fcsses Kreuz, so will ich sagen\""
    },
    {
     "artist": "",
     "downloaded_artists": "",
     "downloaded_titles": "St. Matthew Passion, BWV 244: Teil II. \"Und da sie an die St\u00e4tte kamen\" (Evangelista) - Chori \"Der du den Tempel Gottes zerbrichst\" - \"Desgleichen auch die Hohenpriester\" (Evangelista) - Chori \"Andern hat er geholfen\" -###St. Matthew Passion, BWV 244: Teil II. Aria (Tenor) \"Geduld! Wenn mich falsche Zungen stechen\"",
     "length_seconds": 214040,
     "number": 35,
     "offset": 33120,
     "output_artist": "Johann Sebastian Bach; John Eliot Gardiner, The Monteverdi Choir, The London Oratory Junior Choir, The English Baroque Soloists",
     "output_title": "St. Matthew Passion, BWV 244: Teil II. \"Und da sie an die St\u00e4tte kamen\" (Evangelista) - Chori \"Der du den Tempel Gottes zerbrichst\" - \"Desgleichen auch die Hohenpriester\" (Evangelista) - Chori \"Andern hat er geholfen\" -",
     "sectors": 16050,
     "title": "Teil II. 35 \"Und da sie an die St\u00e4tte kamen\" (Evangelista) - Chori \"Der du den Tempel Gottes zerbrichst\" - \"Desgleichen auch die Hohenpriester\" (Evangelista) - Chori \"Andern hat er geholfen\" -"
    }
   ]
  }
 }
}
